MANIFEST.in
README.txt
setup.py
helloworld/__init__.py
helloworld/hello.py
helloworld/images/__init__.py
helloworld/images/hello.gif
pip_hello_world.egg-info/PKG-INFO
pip_hello_world.egg-info/SOURCES.txt
pip_hello_world.egg-info/dependency_links.txt
pip_hello_world.egg-info/top_level.txt